sqlalchemy_db_helper/__init__.py
sqlalchemy_db_helper/base.py
sqlalchemy_db_helper/helper.py
sqlalchemy_db_helper/mixins.py
sqlalchemy_db_helper/schemas.py
sqlalchemy_db_helper/tps.py
sqlalchemy_db_helper/utils.py
sqlalchemy_db_helper-0.1.8.dist-info/LICENSE
sqlalchemy_db_helper-0.1.8.dist-info/METADATA
sqlalchemy_db_helper-0.1.8.dist-info/WHEEL
sqlalchemy_db_helper-0.1.8.dist-info/RECORD
