Metadata-Version: 2.3
Name: sqlalchemy_db_helper
Version: 0.1.8
Summary: 
Author: Bakminstof
Author-email: bakminstof@yandex.ru
Requires-Python: >=3.12,<4.0
Classifier: Programming Language :: Python :: 3
Classifier: Programming Language :: Python :: 3.12
Classifier: Programming Language :: Python :: 3.13
Provides-Extra: aiosqlite
Provides-Extra: all
Requires-Dist: aiosqlite (>=0.21.0,<0.22.0) ; extra == "aiosqlite" or extra == "all"
Requires-Dist: pydantic (>=2.11.9,<3.0.0)
Requires-Dist: sqlalchemy (>=2.0.43,<3.0.0)
Project-URL: Repository, https://github.com/Bakminstof/sqlalchemy_db_helper
